{
    "header": {
        "code": 0,
        "message": {
            "title": "",
            "detail": ""
        }
    },
    "body": {
        "dataStores": {
            "2d26dfad-56ae-4cf3-ab26-87112f1e": {
                "rowSet": {
                    "primary": [
                        {
                            "ZH": "{Account}",
                            "_t": 3,
                            "XM": "{Name}",
                            "XSXB": "{Sex}",
                            "NL": "{Age}",
                            "SZDW": "{BelongsTo}",
                            "ZYMC": "{Major}",
                            "XSLX": "{Origin}",
                            "ZXSJ": "{Phone}",
                            "SBSJ": "{Today}",
                            "FDYXMX": "{CounselorName}",
                            "JJLXRXM": "{ParentName}",
                            "JJLXRDH": "{ParentPhone}",
                            "JJLXRYBRGX": "{ParentRelation}",
                            "LXZT": "{PositionStatus}",
                            "DQSFJJIA": "{AtHomeOrNot}",
                            "sheng_TEXT": "{ProvinceText}",
                            "sheng": "{Province}",
                            "shi_TEXT": "{CityText}",
                            "shi": "{City}",
                            "quxian_TEXT": "{DistrictText}",
                            "quxian": "{District}",
                            "DQJZDZ": "{Location}",
                            "XQSFYQRBL": "否No",
                            "DRTW": "{Temp}",
                            "CLSJ": "{MeasureTime}",
                            "BRSFFS": "否No",
                            "YWZZ": "无症状No symptoms",
                            "ZZLX": "",
                            "JJGDZ": "否No",
                            "JZGDZ": "否No",
                            "YSGDZ": "否No",
                            "YWZZGDZ": "无症状No symptoms",
                            "ZZLXGDZ": "",
                            "QTZZMS": "",
                            "ZKGDZ": "",
                            "SFJJYXGL": "否No",
                            "JJGLZT": "",
                            "YXGCX": "否No",
                            "JZYXGCZT": "",
                            "SFYSHQZ": "否No",
                            "QZQK": "",
                            "SFDGYQSQ": "否No",
                            "SFJCGYQ": "否No",
                            "SFJQZYQHZ": "否No",
                            "JRSFYJCS": "否No",
                            "EXCASE": "否No",
                            "EXCASECONTACT": "否No",
                            "EXFOURTEENFEVER": "否No",
                            "EXTEST": "否No",
                            "EXTESTRESULT": "否No",
                            "sflxs": "否 No",
                            "sqsfyyq": "否 No",
                            "FXQKGDZ": "",
                            "FXLYD": "",
                            "FXSJ": "",
                            "LXMDD": "",
                            "LXSJ": "",
                            "GRCN": "我承诺以上信息真实准确，并愿意承担相应法律责任。I promise that the above information is true and accurate, and I am willing to bear the corresponding legal responsibility.",
                            "FYZKGDZ": "",
                            "JZGC": "",
                            "JZGLDD": "",
                            "JJYXGC": "",
                            "JJYXGCDD": "",
                            "_o": {
                                "ZH": null,
                                "XM": null,
                                "XSXB": null,
                                "NL": null,
                                "SZDW": null,
                                "ZYMC": null,
                                "XSLX": null,
                                "ZXSJ": null,
                                "SBSJ": null,
                                "FDYXMX": null,
                                "JJLXRXM": null,
                                "JJLXRDH": null,
                                "JJLXRYBRGX": null,
                                "LXZT": null,
                                "DQSFJJIA": null,
                                "sheng_TEXT": null,
                                "sheng": null,
                                "shi_TEXT": null,
                                "shi": null,
                                "quxian_TEXT": null,
                                "quxian": null,
                                "DQJZDZ": null,
                                "XQSFYQRBL": null,
                                "DRTW": null,
                                "CLSJ": null,
                                "BRSFFS": null,
                                "YWZZ": null,
                                "ZZLX": null,
                                "JJGDZ": null,
                                "JZGDZ": null,
                                "YSGDZ": null,
                                "YWZZGDZ": null,
                                "ZZLXGDZ": null,
                                "QTZZMS": null,
                                "ZKGDZ": null,
                                "SFJJYXGL": null,
                                "JJGLZT": null,
                                "YXGCX": null,
                                "JZYXGCZT": null,
                                "SFYSHQZ": null,
                                "QZQK": null,
                                "SFDGYQSQ": null,
                                "SFJCGYQ": null,
                                "SFJQZYQHZ": null,
                                "JRSFYJCS": null,
                                "EXCASE": null,
                                "EXCASECONTACT": null,
                                "EXFOURTEENFEVER": null,
                                "EXTEST": null,
                                "EXTESTRESULT": null,
                                "sflxs": null,
                                "sqsfyyq": null,
                                "FXQKGDZ": null,
                                "FXLYD": null,
                                "FXSJ": null,
                                "LXMDD": null,
                                "LXSJ": null,
                                "GRCN": null,
                                "FYZKGDZ": null,
                                "JZGC": null,
                                "JZGLDD": null,
                                "JJYXGC": null,
                                "JJYXGCDD": null
                            }
                        }
                    ],
                    "filter": [],
                    "delete": []
                },
                "name": "2d26dfad-56ae-4cf3-ab26-87112f1e",
                "pageNumber": 1,
                "pageSize": 2147483647,
                "recordCount": 1,
                "rowSetName": "f4575f2f-e527-419d-8378-235497f9",
                "parameters": {
                    "relatedcontrols": "body_0",
                    "primarykey": "pk_id",
                    "queryds": "2d26dfad-56ae-4cf3-ab26-87112f1e"
                }
            },
            "2d26dfad-56ae-4cf3-ab26-87112f1e_record": {
                "rowSet": {
                    "primary": [
                        {
                            "ZZLX": "",
                            "LXZT": "非学校所在城市Not in the city of the university",
                            "DRTW": "36",
                            "JJGLZT": "",
                            "GRCN": "我承诺以上信息真实准确，并愿意承担相应法律责任。I promise that the above information is true and accurate, and I am willing to bear the corresponding legal responsibility.",
                            "ZXSJ": "17861090607",
                            "pk_id": "-3cbef2d8:1775a3f9663:-bf8",
                            "ZH": "201900600142",
                            "YWZZ": "无症状No symptoms",
                            "JZGDZ": "否No",
                            "ZYMC": "国际政治",
                            "LXMDD": "",
                            "quxian_TEXT": "颍东区",
                            "DQSFJJIA": "在外Away from home",
                            "SZDW": "东北亚学院",
                            "FXQKGDZ": "",
                            "CLSJ": "1612130400000",
                            "SFJCGYQ": "否No",
                            "YWZZGDZ": "无症状No symptoms",
                            "JZYXGCZT": "",
                            "SBSJ": "1612108800000",
                            "YSGDZ": "否No",
                            "shi": "阜阳市",
                            "BRSFFS": "否No",
                            "FDYXMX": "张进",
                            "EXFOURTEENFEVER": "否No",
                            "XSXB": "男",
                            "JJYXGCDD": "",
                            "JJLXRDH": "201900600142",
                            "SFJJYXGL": "否No",
                            "DQJZDZ": "河东街道幸福新村",
                            "NL": "22",
                            "LXSJ": "",
                            "JZGC": "",
                            "FYZKGDZ": "",
                            "JRSFYJCS": "否No",
                            "FXSJ": "",
                            "JJLXRXM": "田从林",
                            "XQSFYQRBL": "否No",
                            "fk_id": "2102011624445154",
                            "JJLXRYBRGX": "父子",
                            "XM": "田野",
                            "JJYXGC": "",
                            "SFJQZYQHZ": "否No",
                            "SFYSHQZ": "否No",
                            "sheng": "安徽省",
                            "XSLX": "内地本科生Mainland undergraduate",
                            "ZZLXGDZ": "",
                            "SFDGYQSQ": "否No",
                            "ZKGDZ": "",
                            "EXTESTRESULT": "否No",
                            "EXCASECONTACT": "否No",
                            "SBSJ_STR": "2021-02-01 00:00:00",
                            "JZGLDD": "",
                            "JJGDZ": "否No",
                            "quxian": "颍东区",
                            "shi_TEXT": "阜阳市",
                            "sqsfyyq": "否 No",
                            "EXTEST": "否No",
                            "EXCASE": "否No",
                            "FXLYD": "",
                            "sflxs": "否 No",
                            "sheng_TEXT": "安徽省",
                            "YXGCX": "否No",
                            "QZQK": "",
                            "CLSJ_STR": "2021-02-01 06:00:00",
                            "QTZZMS": ""
                        }
                    ],
                    "filter": [],
                    "delete": []
                },
                "name": "2d26dfad-56ae-4cf3-ab26-87112f1e_record",
                "pageNumber": 1,
                "pageSize": 2147483647,
                "recordCount": 0,
                "rowSetName": "f4575f2f-e527-419d-8378-235497f9",
                "parameters": {
                    "exist": true,
                    "relatedcontrols": "body_0",
                    "primarykey": "pk_id",
                    "queryds": "2d26dfad-56ae-4cf3-ab26-87112f1e"
                }
            },
            "variable": {
                "rowSet": {
                    "primary": [
                        {
                            "source": "interface",
                            "name": "SYS_USER",
                            "value": "{SysUsername}",
                            "type": "string"
                        },
                        {
                            "source": "interface",
                            "name": "SYS_UNIT",
                            "value": "{SysUnit}",
                            "type": "string"
                        },
                        {
                            "source": "interface",
                            "name": "SYS_DATE",
                            "value": "{SysDate}",
                            "type": "date"
                        },
                        {
                            "name": "1189060d-4465-4b53-89c2-c9f88457.ID_NUMBER",
                            "value": "{Account}"
                        },
                        {
                            "name": "1189060d-4465-4b53-89c2-c9f88457.USER_NAME",
                            "value": "{Name}"
                        },
                        {
                            "name": "666d8a60-7108-4681-829d-545841c3.XB",
                            "value": "{Sex}"
                        },
                        {
                            "name": "666d8a60-7108-4681-829d-545841c3.SZYX",
                            "value": "{BelongsTo}"
                        },
                        {
                            "name": "666d8a60-7108-4681-829d-545841c3.ZYMC",
                            "value": "{Major}"
                        },
                        {
                            "name": "1189060d-4465-4b53-89c2-c9f88457.MOBILE",
                            "value": "{Mobile}"
                        }
                    ],
                    "filter": [],
                    "delete": []
                },
                "name": "variable",
                "pageNumber": 1,
                "pageSize": 2147483647,
                "recordCount": 0,
                "parameters": {}
            }
        },
        "parameters": {
            "formid": "d11d0d9b-d73a-4dad-b3c5-7d44b4ed",
            "status": "select",
            "privilegeId": "7374321285e4d36bbf3d274087454163",
            "seqId": "",
            "service_id": "41d9ad4a-f681-4872-a400-20a3b606d399",
            "process": "674950f5-924b-463d-9eb6-21d5d1b6d9ef",
            "record_fk": "{ForeignKey}",
            "strUserId": "",
            "strUserIdCC": "",
            "nextActId": ""
        }
    }
}